iam_policy_lint/__init__.py
iam_policy_lint/cli.py
iam_policy_lint/linter.py
iam_policy_lint/validator.py
iam_policy_lint-0.3.2.dist-info/METADATA
iam_policy_lint-0.3.2.dist-info/WHEEL
iam_policy_lint-0.3.2.dist-info/entry_points.txt
iam_policy_lint-0.3.2.dist-info/licenses/LICENSE
iam_policy_lint-0.3.2.dist-info/RECORD
