Metadata-Version: 2.4
Name: iam-policy-lint
Version: 0.3.2
Summary: A comprehensive tool for linting and validating AWS IAM policies in JSON and YAML formats using Parliament
Project-URL: Homepage, https://github.com/gilandose/iam-policy-lint
Project-URL: Repository, https://github.com/gilandose/iam-policy-lint
Project-URL: Issues, https://github.com/gilandose/iam-policy-lint/issues
Project-URL: Documentation, https://github.com/gilandose/iam-policy-lint#readme
Project-URL: Changelog, https://github.com/gilandose/iam-policy-lint/releases
Author-email: Richard Gilmore <richard.gilmore@gmail.com>
License: MIT
License-File: LICENSE
Keywords: aws,embedded,governance,iam,json,lint,parliament,policy,security,validation,yaml
Classifier: Development Status :: 4 - Beta
Classifier: Environment :: Console
Classifier: Intended Audience :: Developers
Classifier: Intended Audience :: System Administrators
Classifier: License :: OSI Approved :: MIT License
Classifier: Operating System :: OS Independent
Classifier: Programming Language :: Python :: 3
Classifier: Programming Language :: Python :: 3.9
Classifier: Programming Language :: Python :: 3.10
Classifier: Programming Language :: Python :: 3.11
Classifier: Programming Language :: Python :: 3.12
Classifier: Topic :: Security
Classifier: Topic :: Software Development :: Quality Assurance
Classifier: Topic :: System :: Systems Administration
Requires-Python: >=3.9
Requires-Dist: click>=8.0.0
Requires-Dist: parliament>=1.6.4
Requires-Dist: pyyaml>=6.0.0
Requires-Dist: setuptools>=80.9.0
